small_world_propensity/__init__.py
small_world_propensity/small_world_propensity.py
small_world_propensity-0.1.17.dist-info/LICENSE
small_world_propensity-0.1.17.dist-info/METADATA
small_world_propensity-0.1.17.dist-info/WHEEL
small_world_propensity-0.1.17.dist-info/RECORD
