Metadata-Version: 2.1
Name: small-world-propensity
Version: 0.1.17
Summary: A python package designed to calculate the small-world propensity of a weighted, undirected network. Translated from the MATLAB version featured in Muldoon et al.
Home-page: https://github.com/rkdan/small_world_propensity
License: GPL-3.0-only
Author: Ryan Daniels
Requires-Python: >=3.10,<4.0
Classifier: License :: OSI Approved :: GNU General Public License v3 (GPLv3)
Classifier: Programming Language :: Python :: 3
Classifier: Programming Language :: Python :: 3.10
Classifier: Programming Language :: Python :: 3.11
Classifier: Programming Language :: Python :: 3.12
Requires-Dist: numpy (>=1.24.3,<2.0.0)
Requires-Dist: pandas (>=2.0.2,<3.0.0)
Requires-Dist: tqdm (>=4.65.0,<5.0.0)
Project-URL: Repository, https://github.com/rkdan/small_world_propensity
